gdetect/__init__.py
gdetect/__main__.py
gdetect/api.py
gdetect/cli.py
gdetect/consts.py
gdetect/exceptions.py
gdetect/log.py
gdetect/py.typed
gdetect/stream.py
gdetect-0.9.0.dist-info/licenses/LICENSE
gdetect-0.9.0.dist-info/METADATA
gdetect-0.9.0.dist-info/WHEEL
gdetect-0.9.0.dist-info/entry_points.txt
gdetect-0.9.0.dist-info/top_level.txt
gdetect-0.9.0.dist-info/RECORD
