Metadata-Version: 2.4
Name: gdetect
Version: 0.9.0
Summary: Library and CLI for GLIMPS Detect API
Author-email: GLIMPS dev core team <contact@glimps.re>
Keywords: python,glimps,detection,gmalware,malware,gdetect
Classifier: Development Status :: 5 - Production/Stable
Classifier: Programming Language :: Python :: 3
Classifier: Operating System :: MacOS :: MacOS X
Classifier: Operating System :: Microsoft :: Windows
Classifier: Operating System :: POSIX :: Linux
Classifier: License :: OSI Approved :: MIT License
Classifier: Programming Language :: Python :: 3.10
Classifier: Programming Language :: Python :: 3.11
Classifier: Programming Language :: Python :: 3.12
Classifier: Programming Language :: Python :: 3.13
Requires-Python: >=3.10
License-File: LICENSE
Requires-Dist: click~=8.0
Requires-Dist: click-default-group~=1.2
Requires-Dist: requests~=2.32
Requires-Dist: rich~=14.1
Provides-Extra: dev
Requires-Dist: pytest==8.1.1; extra == "dev"
Requires-Dist: pytest-cov==4.1.0; extra == "dev"
Dynamic: license-file
